riichienv/__init__.py
riichienv/_riichienv.cpython-312-darwin.so
riichienv/_riichienv.pyi
riichienv/action.py
riichienv/agents/__init__.py
riichienv/agents/random_agent.py
riichienv/convert.py
riichienv/game_mode.py
riichienv/game_modes.py
riichienv/hand.py
riichienv/log.py
riichienv/visualizer/__init__.py
riichienv/visualizer/assets/viewer.js.gz
riichienv/visualizer/viewer.py
riichienv-0.2.0.dist-info/METADATA
riichienv-0.2.0.dist-info/WHEEL
riichienv-0.2.0.dist-info/entry_points.txt
riichienv-0.2.0.dist-info/licenses/LICENSE
riichienv-0.2.0.dist-info/RECORD
