Metadata-Version: 2.4
Name: riichienv
Version: 0.2.0
Classifier: Programming Language :: Python :: 3
Classifier: Operating System :: OS Independent
Requires-Dist: pyyaml>=6.0.3
Requires-Dist: ipython
License-File: LICENSE
Summary: A High-Performance Research Environment for Riichi Mahjong
Author-email: Kohei Ozaki <19337+smly@users.noreply.github.com>
License-Expression: Apache-2.0
Requires-Python: >=3.10, <3.15
Project-URL: Homepage, https://github.com/smly/RiichiEnv
Project-URL: Issues, https://github.com/smly/RiichiEnv/issues
